performer_pytorch/__init__.py
performer_pytorch/autoregressive_wrapper.py
performer_pytorch/performer_enc_dec.py
performer_pytorch/performer_pytorch.py
performer_pytorch/reversible.py
performer_pytorch-1.1.4.dist-info/LICENSE
performer_pytorch-1.1.4.dist-info/METADATA
performer_pytorch-1.1.4.dist-info/WHEEL
performer_pytorch-1.1.4.dist-info/top_level.txt
performer_pytorch-1.1.4.dist-info/RECORD
