Metadata-Version: 2.1
Name: performer-pytorch
Version: 1.1.4
Summary: Performer - Pytorch
Home-page: https://github.com/lucidrains/performer-pytorch
Author: Phil Wang
Author-email: lucidrains@gmail.com
License: MIT
Keywords: artificial intelligence,attention mechanism,efficient attention,transformers
Platform: UNKNOWN
Classifier: Development Status :: 4 - Beta
Classifier: Intended Audience :: Developers
Classifier: Topic :: Scientific/Engineering :: Artificial Intelligence
Classifier: License :: OSI Approved :: MIT License
Classifier: Programming Language :: Python :: 3.6
License-File: LICENSE
